mf/__init__.py
mf/cli.py
memoflow-0.1.0.dist-info/METADATA
memoflow-0.1.0.dist-info/WHEEL
memoflow-0.1.0.dist-info/entry_points.txt
memoflow-0.1.0.dist-info/top_level.txt
memoflow-0.1.0.dist-info/RECORD
