Metadata-Version: 2.4
Name: memoflow
Version: 0.1.0
Summary: MemoFlow - Your Second Brain: A command-line workflow management tool
Author: MemoFlow Team
License: MIT
Keywords: workflow,productivity,markdown,git,cli
Classifier: Development Status :: 4 - Beta
Classifier: Intended Audience :: Developers
Classifier: License :: OSI Approved :: MIT License
Classifier: Programming Language :: Python :: 3
Classifier: Programming Language :: Python :: 3.9
Classifier: Programming Language :: Python :: 3.10
Classifier: Programming Language :: Python :: 3.11
Classifier: Programming Language :: Python :: 3.12
Requires-Python: >=3.9
Requires-Dist: typer>=0.9.0
Requires-Dist: gitpython>=3.1.40
Requires-Dist: pyyaml>=6.0
Requires-Dist: python-frontmatter>=1.0.0
Requires-Dist: python-dateutil>=2.8.0
Provides-Extra: graph
Requires-Dist: nebula3-python>=3.7.0; extra == "graph"
Provides-Extra: tui
Requires-Dist: rich>=13.0.0; extra == "tui"
Requires-Dist: textual>=0.40.0; extra == "tui"
Provides-Extra: dev
Requires-Dist: pytest>=7.4.0; extra == "dev"
Requires-Dist: pytest-cov>=4.1.0; extra == "dev"
Requires-Dist: pytest-mock>=3.11.0; extra == "dev"
